pyHaveIBeenPwned/__init__.py
pyHaveIBeenPwned-0.1.16.dist-info/LICENSE
pyHaveIBeenPwned-0.1.16.dist-info/METADATA
pyHaveIBeenPwned-0.1.16.dist-info/WHEEL
pyHaveIBeenPwned-0.1.16.dist-info/top_level.txt
pyHaveIBeenPwned-0.1.16.dist-info/RECORD
