Metadata-Version: 2.1
Name: pyHaveIBeenPwned
Version: 0.1.16
Summary: Library to query HaveIBeenPwned.com with handeling for CloudFlare anti-bot 
Home-page: https://github.com/Hackman238/pyHaveIBeenPwned
Author: Shane Scott
Author-email: gs@shanewilliamscott.com
Classifier: Development Status :: 3 - Alpha
Classifier: Intended Audience :: Developers
Classifier: License :: OSI Approved :: GNU General Public License v2 (GPLv2)
Classifier: Programming Language :: Python :: 3.9
Classifier: Programming Language :: Python :: 3.10
Classifier: Programming Language :: Python :: 3.11
Classifier: Operating System :: Microsoft :: Windows
Classifier: Operating System :: MacOS :: MacOS X
Classifier: Operating System :: POSIX :: Linux
Classifier: Topic :: Software Development :: Libraries
Requires-Python: >=3.9
License-File: LICENSE
